litegrade/__init__.py
litegrade/commondriver.py
litegrade/htmldriver.py
litegrade/notebookdriver.py
litegrade/questiondriver.py
test/__init__.py
test/commondriver.py
test/htmldriver.py
test/notebookdriver.py
test/questiondriver.py
test/run_tests.py
test/test_htmldriver.py
litegrade-0.0.62.dist-info/LICENSE
litegrade-0.0.62.dist-info/METADATA
litegrade-0.0.62.dist-info/WHEEL
litegrade-0.0.62.dist-info/top_level.txt
litegrade-0.0.62.dist-info/RECORD
