Metadata-Version: 2.1
Name: litegrade
Version: 0.0.62
Summary: An intuitive grading tool for IPython notebooks
Home-page: https://github.com/2justinmorgan/litegrade
Author: Justin Morgan
Author-email: 2justinmorgan@gmail.com
License: UNKNOWN
Platform: UNKNOWN
Classifier: Programming Language :: Python :: 3
Classifier: License :: OSI Approved :: MIT License
Classifier: Operating System :: OS Independent
Requires-Python: >=3.6
